perch_hoplite/agile/1_embed_audio_v2.ipynb
perch_hoplite/agile/2_agile_modeling_v2.ipynb
perch_hoplite/agile/audio_loader.py
perch_hoplite/agile/classifier.py
perch_hoplite/agile/classifier_data.py
perch_hoplite/agile/colab_utils.py
perch_hoplite/agile/convert_legacy.py
perch_hoplite/agile/embed.py
perch_hoplite/agile/embedding_display.py
perch_hoplite/agile/ingest_annotations.py
perch_hoplite/agile/metrics.py
perch_hoplite/agile/source_info.py
perch_hoplite/agile/tests/classifier_data_test.py
perch_hoplite/agile/tests/classifier_test.py
perch_hoplite/agile/tests/convert_legacy_test.py
perch_hoplite/agile/tests/embed_test.py
perch_hoplite/agile/tests/embedding_display_test.py
perch_hoplite/agile/tests/ingest_annotations_test.py
perch_hoplite/agile/tests/metrics_test.py
perch_hoplite/agile/tests/source_info_test.py
perch_hoplite/agile/tests/test_utils.py
perch_hoplite/agile/tests/testdata/config.json
perch_hoplite/agile/tests/testdata/embeddings-1730850444-00000-of-00001
perch_hoplite/agile/tests/testdata/hawaii.csv
perch_hoplite/audio_io.py
perch_hoplite/db/README.md
perch_hoplite/db/brutalism.py
perch_hoplite/db/db_loader.py
perch_hoplite/db/in_mem_impl.py
perch_hoplite/db/interface.py
perch_hoplite/db/score_functions.py
perch_hoplite/db/search_results.py
perch_hoplite/db/sqlite_usearch_impl.py
perch_hoplite/db/tests/brutalism_test.py
perch_hoplite/db/tests/hoplite_test.py
perch_hoplite/db/tests/test_utils.py
perch_hoplite/path_utils.py
perch_hoplite/taxonomy/README.md
perch_hoplite/taxonomy/annotations.py
perch_hoplite/taxonomy/annotations_fns.py
perch_hoplite/taxonomy/class_utils.py
perch_hoplite/taxonomy/ebird.py
perch_hoplite/taxonomy/namespace.py
perch_hoplite/taxonomy/namespace_db.py
perch_hoplite/taxonomy/namespace_db_test.py
perch_hoplite/taxonomy/taxonomy_database.json
perch_hoplite/zoo/README.md
perch_hoplite/zoo/aves_model.py
perch_hoplite/zoo/handcrafted_features_model.py
perch_hoplite/zoo/hub.py
perch_hoplite/zoo/model_configs.py
perch_hoplite-0.1.3.dist-info/METADATA
perch_hoplite-0.1.3.dist-info/WHEEL
perch_hoplite-0.1.3.dist-info/licenses/AUTHORS
perch_hoplite-0.1.3.dist-info/licenses/LICENSE
perch_hoplite-0.1.3.dist-info/RECORD
