Metadata-Version: 2.4
Name: perch-hoplite
Version: 0.1.3
Summary: Tooling for agile modeling on large machine perception embedding databases.
License: Apache License
License-File: AUTHORS
License-File: LICENSE
Author: tom denton
Author-email: tomdenton@google.com
Requires-Python: >=3.10
Classifier: License :: Other/Proprietary License
Classifier: Programming Language :: Python :: 3
Classifier: Programming Language :: Python :: 3.10
Classifier: Programming Language :: Python :: 3.11
Classifier: Programming Language :: Python :: 3.12
Requires-Dist: absl-py (>=1.4.0,<2.0.0)
Requires-Dist: etils[epath] (>=1.5.0,<2.0.0)
Requires-Dist: imageio (>=2.5.0,<3.0.0)
Requires-Dist: ipywidgets (>=8.1,<9.0)
Requires-Dist: kagglehub (>=0.3,<0.4)
Requires-Dist: librosa (>=0.11,<0.12)
Requires-Dist: matplotlib (>=3.6.1,<4.0.0)
Requires-Dist: ml-collections (>=0.1.1,<0.2.0)
Requires-Dist: notebook (>=7.4,<8.0)
Requires-Dist: numpy (>=2.0,<2.1)
Requires-Dist: pandas[gcp] (>=2.1.1,<3.0.0)
Requires-Dist: usearch (>=2.17,<3.0)
